pydle/__init__.py
pydle/client.py
pydle/connection.py
pydle/features/__init__.py
pydle/features/account.py
pydle/features/ctcp.py
pydle/features/ircv3/__init__.py
pydle/features/ircv3/cap.py
pydle/features/ircv3/ircv3_1.py
pydle/features/ircv3/ircv3_2.py
pydle/features/ircv3/ircv3_3.py
pydle/features/ircv3/metadata.py
pydle/features/ircv3/monitor.py
pydle/features/ircv3/sasl.py
pydle/features/ircv3/tags.py
pydle/features/isupport.py
pydle/features/rfc1459/__init__.py
pydle/features/rfc1459/client.py
pydle/features/rfc1459/parsing.py
pydle/features/rfc1459/protocol.py
pydle/features/rpl_whoishost/__init__.py
pydle/features/rpl_whoishost/rpl_whoishost.py
pydle/features/tls.py
pydle/features/whox.py
pydle/protocol.py
pydle/utils/__init__.py
pydle/utils/_args.py
pydle/utils/irccat.py
pydle/utils/run.py
pydle-1.1.0.dist-info/LICENSE.md
pydle-1.1.0.dist-info/METADATA
pydle-1.1.0.dist-info/WHEEL
pydle-1.1.0.dist-info/entry_points.txt
pydle-1.1.0.dist-info/RECORD
