Metadata-Version: 2.3
Name: pydle
Version: 1.1.0
Summary: A compact, flexible, and standards-abiding IRC library for python3.
License: BSD-3-Clause
Keywords: irc,library,python3,compact,flexible
Author: Shiz
Author-email: hi@shiz.me
Maintainer: polyfloyd
Maintainer-email: floyd@polyfloyd.net
Requires-Python: >= 3.10
Classifier: License :: OSI Approved :: BSD License
Classifier: Programming Language :: Python :: 3
Classifier: Programming Language :: Python :: 3.10
Classifier: Programming Language :: Python :: 3.11
Classifier: Programming Language :: Python :: 3.12
Classifier: Programming Language :: Python :: 3.13
Provides-Extra: dev
Provides-Extra: sasl
Requires-Dist: Sphinx (>=5.0.2,<5.1.0) ; extra == "dev"
Requires-Dist: build ; extra == "dev"
Requires-Dist: pure-sasl (>=0.6.1) ; extra == "sasl"
Requires-Dist: pytest ; extra == "dev"
Requires-Dist: pytest-asyncio ; extra == "dev"
Requires-Dist: sphinx-rtd-theme (>=1.0.0,<1.1.0) ; extra == "dev"
Project-URL: Documentation, https://pydle.readthedocs.io/
Project-URL: issues, https://github.com/shizmob/pydle/issues
Project-URL: source, https://github.com/shizmob/pydle
